Metadata-Version: 1.1
Name: replace-me
Version: 0.1.4
Summary: Modify your own source code with this piece of Python black magic
Home-page: https://github.com/boppreh/replace_me
Author: BoppreH
Author-email: boppreh@gmail.com
License: MIT
Platform: UNKNOWN
Classifier: Development Status :: 3 - Alpha
Classifier: License :: OSI Approved :: MIT License
Classifier: Operating System :: Microsoft :: Windows
Classifier: Operating System :: Unix
Classifier: Operating System :: MacOS :: MacOS X
Classifier: Programming Language :: Python :: 3
Classifier: Topic :: Software Development :: Libraries :: Python Modules
Classifier: Topic :: Utilities
